LICENSE
MANIFEST.in
README.rst
setup.py
examples/mypicks.pickle
examples/pycker_viewer.png
examples/pycker_viewer.py
examples/data/19910914_01.segy
examples/data/19910914_02.segy
examples/data/19910914_03.segy
examples/data/19910914_04.segy
examples/data/19910914_05.segy
examples/data/19910914_06.segy
examples/data/19910914_07.segy
examples/data/19910914_08.segy
examples/data/19910914_09.segy
examples/data/19910914_10.segy
pycker/__init__.py
pycker/pick.py
pycker/quantity_error.py
pycker/read_stream.py
pycker/wiggle.py
pycker.egg-info/PKG-INFO
pycker.egg-info/SOURCES.txt
pycker.egg-info/dependency_links.txt
pycker.egg-info/requires.txt
pycker.egg-info/top_level.txt
pycker/__pycache__/__init__.cpython-35.pyc
pycker/__pycache__/pick.cpython-35.pyc
pycker/__pycache__/quantity_error.cpython-35.pyc
pycker/__pycache__/read_stream.cpython-35.pyc
pycker/__pycache__/wiggle.cpython-35.pyc
pycker/gui/__init__.py
pycker/gui/gui.py
pycker/gui/ttk_spinbox.py
pycker/gui/__pycache__/__init__.cpython-35.pyc
pycker/gui/__pycache__/__init__.cpython-36.pyc
pycker/gui/__pycache__/gui.cpython-35.pyc
pycker/gui/__pycache__/gui.cpython-36.pyc
pycker/gui/__pycache__/ttk_spinbox.cpython-35.pyc
pycker/gui/__pycache__/ttk_spinbox.cpython-36.pyc