Metadata-Version: 1.1
Name: pycker
Version: 1.1.1
Summary: Pycker
Home-page: https://github.com/keurfonluu/pycker
Author: Keurfon LUU
Author-email: keurfon.luu@mines-paristech.fr
License: MIT License
Platform: UNKNOWN
Classifier: Programming Language :: Python
Classifier: Development Status :: 5 - Production/Stable
Classifier: License :: OSI Approved :: MIT License
Classifier: Natural Language :: English
Classifier: Operating System :: OS Independent
Classifier: Intended Audience :: Science/Research
Classifier: Topic :: Scientific/Engineering
Classifier: Topic :: Scientific/Engineering :: Mathematics
